{
  "kind": "singleType",
  "collectionName": "gallery_pages",
  "info": {
    "singularName": "gallery-page",
    "pluralName": "gallery-pages",
    "displayName": "gallery page"
  },
  "options": {
    "draftAndPublish": true
  },
  "pluginOptions": {
    "i18n": {
      "localized": true
    }
  },
  "attributes": {
    "pagehero": {
      "type": "component",
      "pluginOptions": {
        "i18n": {
          "localized": true
        }
      },
      "component": "shared.page-hero",
      "repeatable": false,
      "required": true
    },
    "sectionheader": {
      "type": "component",
      "pluginOptions": {
        "i18n": {
          "localized": true
        }
      },
      "component": "shared.section-header",
      "repeatable": false,
      "required": true
    },
    "description": {
      "type": "text",
      "pluginOptions": {
        "i18n": {
          "localized": true
        }
      },
      "default": "Choose a media type to view organized albums from institute programmes, field work, research events, and knowledge sharing activities.",
      "minLength": 100,
      "maxLength": 255,
      "required": true
    },
    "photogallery": {
      "type": "component",
      "pluginOptions": {
        "i18n": {
          "localized": true
        }
      },
      "component": "shared.albumcard",
      "repeatable": false,
      "required": true
    },
    "videogallery": {
      "type": "component",
      "pluginOptions": {
        "i18n": {
          "localized": true
        }
      },
      "component": "shared.albumcard",
      "repeatable": false,
      "required": true
    }
  }
}
